aws_encryption_sdk_cli/__init__.py
aws_encryption_sdk_cli/compatability.py
aws_encryption_sdk_cli/exceptions.py
aws_encryption_sdk_cli/key_providers.py
aws_encryption_sdk_cli/internal/__init__.py
aws_encryption_sdk_cli/internal/arg_parsing.py
aws_encryption_sdk_cli/internal/identifiers.py
aws_encryption_sdk_cli/internal/io_handling.py
aws_encryption_sdk_cli/internal/logging_utils.py
aws_encryption_sdk_cli/internal/master_key_parsing.py
aws_encryption_sdk_cli/internal/metadata.py
aws_encryption_sdk_cli/internal/mypy_types.py
aws_encryption_sdk_cli-4.2.0.dist-info/LICENSE
aws_encryption_sdk_cli-4.2.0.dist-info/METADATA
aws_encryption_sdk_cli-4.2.0.dist-info/WHEEL
aws_encryption_sdk_cli-4.2.0.dist-info/entry_points.txt
aws_encryption_sdk_cli-4.2.0.dist-info/top_level.txt
aws_encryption_sdk_cli-4.2.0.dist-info/RECORD
