Metadata-Version: 2.1
Name: aws-encryption-sdk-cli
Version: 4.2.0
Summary: This command line tool can be used to encrypt and decrypt files and directories using the AWS Encryption SDK.
Home-page: http://aws-encryption-sdk-cli.readthedocs.io/en/latest/
Author: Amazon Web Services
Author-email: aws-cryptools@amazon.com
Maintainer: Amazon Web Services
License: Apache License 2.0
Keywords: aws-encryption-sdk aws kms encryption cli command line
Platform: UNKNOWN
Classifier: Development Status :: 5 - Production/Stable
Classifier: Intended Audience :: Developers
Classifier: Natural Language :: English
Classifier: License :: OSI Approved :: Apache Software License
Classifier: Programming Language :: Python
Classifier: Programming Language :: Python :: 3
Classifier: Programming Language :: Python :: 3.8
Classifier: Programming Language :: Python :: 3.9
Classifier: Programming Language :: Python :: 3.10
Classifier: Programming Language :: Python :: 3.11
Classifier: Programming Language :: Python :: 3.12
Classifier: Programming Language :: Python :: Implementation :: CPython
Classifier: Topic :: Security
Classifier: Topic :: Security :: Cryptography
License-File: LICENSE
Requires-Dist: base64io (>=1.0.1)
Requires-Dist: aws-encryption-sdk (~=3.1)
Requires-Dist: setuptools
Requires-Dist: attrs (>=17.1.0)
